libname/__init__.py
libname/hello.py
helloev31-0.0.9.dist-info/METADATA
helloev31-0.0.9.dist-info/WHEEL
helloev31-0.0.9.dist-info/top_level.txt
helloev31-0.0.9.dist-info/RECORD
